storify/__init__.py
storify/exceptions.py
storify/logger.py
storify/model.py
storify/database/__init__.py
storify/database/backups.py
storify-0.0.11.dist-info/LICENSE
storify-0.0.11.dist-info/METADATA
storify-0.0.11.dist-info/WHEEL
storify-0.0.11.dist-info/top_level.txt
storify-0.0.11.dist-info/RECORD
