Metadata-Version: 2.1
Name: storify
Version: 0.0.11
Summary: A lightweight database system for Python
Home-page: https://github.com/benbaptist/storify
Author: Ben Baptist
Author-email: sawham6@gmail.com
License: MIT
Platform: UNKNOWN
Classifier: Development Status :: 3 - Alpha
Classifier: Intended Audience :: Developers
Classifier: License :: OSI Approved :: MIT License
Classifier: Programming Language :: Python :: 3
Classifier: Programming Language :: Python :: 3.7
Classifier: Programming Language :: Python :: 3.8
Classifier: Programming Language :: Python :: 3.9
Classifier: Programming Language :: Python :: 3.10
Requires-Dist: msgpack
